{"nodes": [{"id": "new_page_newarticleincategory", "label": "NewArticleInCategory", "file_type": "code", "source_file": "erp/app/(admin)/r/[category]/new/page.tsx", "source_location": "8", "source_url": null, "captured_at": null, "author": null, "contributor": null}], "edges": [{"source": "new_page_newarticleincategory", "target": "media_listmedia", "relation": "calls", "confidence": "EXTRACTED", "confidence_score": 1.0, "source_file": "erp/app/(admin)/r/[category]/new/page.tsx", "source_location": "22", "weight": 1.0}, {"source": "new_page_newarticleincategory", "target": "article_form_articleform", "relation": "references", "confidence": "EXTRACTED", "confidence_score": 1.0, "source_file": "erp/app/(admin)/r/[category]/new/page.tsx", "source_location": "37", "weight": 1.0}], "hyperedges": []}