{"nodes": [{"id": "hover_arrow_hoverarrow", "label": "HoverArrow", "file_type": "code", "source_file": "web/components/hover-arrow.tsx", "source_location": "8", "source_url": null, "captured_at": null, "author": null, "contributor": null}], "edges": [{"source": "hover_arrow_hoverarrow", "target": "page_header_pageheader", "relation": "semantically_similar_to", "confidence": "INFERRED", "confidence_score": 0.65, "source_file": "web/components/hover-arrow.tsx", "source_location": "8", "weight": 1.0}], "hyperedges": []}